nocturn/__init__.py
nocturn/exceptions.py
nocturn/wallet.py
nocturn-1.0.0.dist-info/LICENSE
nocturn-1.0.0.dist-info/METADATA
nocturn-1.0.0.dist-info/WHEEL
nocturn-1.0.0.dist-info/top_level.txt
nocturn-1.0.0.dist-info/RECORD
