Metadata-Version: 2.2
Name: nocturn
Version: 1.0.0
Summary: A Python-based lightweight crypto wallet for Ethereum, Binance Smart Chain, and Polygon.
Home-page: https://github.com/suryanshsinh/nocturn
Author: Suryanshsinh Sisodiya
Author-email: suryanshsinhsisodiya@gmail.com
License: MIT
Classifier: Programming Language :: Python :: 3
Classifier: License :: OSI Approved :: MIT License
Classifier: Operating System :: OS Independent
Requires-Python: >=3.6
License-File: LICENSE
Requires-Dist: web3
Requires-Dist: eth-account
Requires-Dist: mnemonic
Requires-Dist: bip32utils
Requires-Dist: requests
Dynamic: author
Dynamic: author-email
Dynamic: classifier
Dynamic: description
Dynamic: description-content-type
Dynamic: home-page
Dynamic: license
Dynamic: requires-dist
Dynamic: requires-python
Dynamic: summary
